MANIFEST.in
README.rst
setup.py
django_ideler_mfa.egg-info/PKG-INFO
django_ideler_mfa.egg-info/SOURCES.txt
django_ideler_mfa.egg-info/dependency_links.txt
django_ideler_mfa.egg-info/not-zip-safe
django_ideler_mfa.egg-info/requires.txt
django_ideler_mfa.egg-info/top_level.txt
ideler_mfa/__init__.py
ideler_mfa/admin.py
ideler_mfa/apps.py
ideler_mfa/decorators.py
ideler_mfa/forms.py
ideler_mfa/middleware.py
ideler_mfa/models.py
ideler_mfa/settings.py
ideler_mfa/urls.py
ideler_mfa/utils.py
ideler_mfa/views.py
ideler_mfa/locale/de/LC_MESSAGES/django.mo
ideler_mfa/locale/de/LC_MESSAGES/django.po
ideler_mfa/methods/__init__.py
ideler_mfa/methods/otp.py
ideler_mfa/methods/totp.py
ideler_mfa/migrations/0001_initial.py
ideler_mfa/migrations/0002_onetimepassword_config.py
ideler_mfa/migrations/__init__.py
ideler_mfa/static/ideler_mfa/admin/css/ideler_mfa.css
ideler_mfa/templates/admin/base_site.html
ideler_mfa/templates/ideler_mfa/configure.html
ideler_mfa/templates/ideler_mfa/disable.html
ideler_mfa/templates/ideler_mfa/select.html
ideler_mfa/templates/ideler_mfa/verify.html
ideler_mfa/templates/ideler_mfa/admin/index.html
ideler_mfa/templatetags/__init__.py
ideler_mfa/templatetags/ideler_mfa_tags.py