Metadata-Version: 2.1
Name: django-ideler-mfa
Version: 0.0.18
Summary: Multi-factor authentication for Django.
Home-page: https://git.ideler.de/python/django-ideler-mfa
Author: Yannik Weiß
Author-email: yannik.weiss@ideler.de
License: UNKNOWN
Platform: UNKNOWN
